MANIFEST.in
README.rst
setup.cfg
setup.py
src/http_crawler/__init__.py
src/http_crawler.egg-info/PKG-INFO
src/http_crawler.egg-info/SOURCES.txt
src/http_crawler.egg-info/dependency_links.txt
src/http_crawler.egg-info/requires.txt
src/http_crawler.egg-info/top_level.txt