Metadata-Version: 1.0
Name: http-crawler
Version: 0.2.0
Summary: A library for crawling websites
Home-page: http://github.com/inglesp/http-crawler
Author: Peter Inglesby
Author-email: peter.inglesby@gmail.com
License: License :: OSI Approved :: MIT License
Platform: UNKNOWN
